amber/BasicGeometries.py
amber/BetaDistributionCalibration.py
amber/CONFIG_default.txt
amber/ReadAndWrite.py
amber/RunTopas.py
amber/ScalarField.py
amber/Terminal.py
amber/__init__.py
amber/cell.py
amber/config.py
amber/config_instance.py
amber/process.py
amber/save_alpha_dataframe2.csv
amber/save_alpha_dataframe6.csv
amber/save_beta_dataframe2.csv
amber/save_beta_dataframe6.csv
amber/vessel.py
amber/voxel.py
amber/world.py
amber/Micro-Oxygenation/BetaDistributionCalibration.py
amber/Micro-Oxygenation/__init__.py
amber/Micro-Oxygenation/save_alpha_dataframe6.csv
amber/Micro-Oxygenation/save_beta_dataframe6.csv
src/BasicGeometries.py
src/Cell.py
src/Process.py
src/ReadAndWrite.py
src/RunTopas.py
src/ScalarField.py
src/Terminal.py
src/Vessel.py
src/Voxel.py
src/World.py
src/__init__.py
src/config.py
src/config_instance.py
src/Micro-Oxygenation/BetaDistributionCalibration.py
src/Micro-Oxygenation/__init__.py
OncoAMBER-1.3.3.dist-info/METADATA
OncoAMBER-1.3.3.dist-info/WHEEL
OncoAMBER-1.3.3.dist-info/top_level.txt
OncoAMBER-1.3.3.dist-info/RECORD
