Metadata-Version: 2.1
Name: OncoAMBER
Version: 1.3.3
Summary: Agent-based model of tumor growth and response to radiation therapy
Home-page: https://github.com/lvkunz/AMBER
Author: Louis Kunz
Author-email: lvkunz@mgh.harvard.edu
License: MIT
Classifier: License :: OSI Approved :: MIT License
Classifier: Operating System :: MacOS
Classifier: Operating System :: Microsoft :: Windows
Classifier: Programming Language :: Python
Classifier: Programming Language :: Python :: 3
Classifier: Programming Language :: Python :: 3.6
Classifier: Programming Language :: Python :: Implementation :: CPython
Classifier: Programming Language :: Python :: Implementation :: PyPy
Requires-Python: >=3.8.2
Requires-Dist: numpy
Requires-Dist: pandas
Requires-Dist: scipy
Provides-Extra: plots
Requires-Dist: matplotlib ; extra == 'plots'
Requires-Dist: seaborn ; extra == 'plots'
